tests/helpers/__init__.py
tests/helpers/test_validation.py
tests/lib/__init__.py
tests/lib/managers/__init__.py
tests/lib/managers/test_docker_manager.py
tests/lib/nodes/__init__.py
tests/lib/nodes/mocks/__init__.py
tests/lib/nodes/mocks/test_mocks.py
tests/lib/nodes/services/__init__.py
tests/lib/nodes/services/test_services.py
tests/lib/nodes/services/docker/__init__.py
tests/lib/nodes/services/docker/test_docker_runnable_service.py
touchstone/__init__.py
touchstone/bootstrap.py
touchstone/cli.py
touchstone/common.py
touchstone/develop.py
touchstone/init.py
touchstone/run.py
touchstone/helpers/__init__.py
touchstone/helpers/http.py
touchstone/helpers/validation.py
touchstone/lib/__init__.py
touchstone/lib/exceptions.py
touchstone/lib/test.py
touchstone/lib/tests.py
touchstone/lib/touchstone_test.py
touchstone/lib/ts_context.py
touchstone/lib/configurers/BasicConfigurer.py
touchstone/lib/configurers/FileConfigurer.py
touchstone/lib/configurers/__init__.py
touchstone/lib/configurers/i_configurable.py
touchstone/lib/configurers/service_config.py
touchstone/lib/configurers/touchstone_config.py
touchstone/lib/health_checks/__init__.py
touchstone/lib/health_checks/blocking_health_check.py
touchstone/lib/health_checks/docker_health_check.py
touchstone/lib/health_checks/http_health_check.py
touchstone/lib/health_checks/i_health_checkable.py
touchstone/lib/listeners/__init__.py
touchstone/lib/listeners/i_services_available_listener.py
touchstone/lib/managers/__init__.py
touchstone/lib/managers/docker_manager.py
touchstone/lib/networking/__init__.py
touchstone/lib/networking/docker_network.py
touchstone/lib/networking/i_network.py
touchstone/lib/nodes/__init__.py
touchstone/lib/nodes/i_networkable.py
touchstone/lib/nodes/deps/__init__.py
touchstone/lib/nodes/deps/dep_factory.py
touchstone/lib/nodes/deps/deps.py
touchstone/lib/nodes/deps/i_dependency.py
touchstone/lib/nodes/deps/i_runnable.py
touchstone/lib/nodes/deps/behaviors/__init__.py
touchstone_testing-1.4.2.dist-info/METADATA
touchstone_testing-1.4.2.dist-info/WHEEL
touchstone_testing-1.4.2.dist-info/entry_points.txt
touchstone_testing-1.4.2.dist-info/top_level.txt
touchstone_testing-1.4.2.dist-info/RECORD
