Metadata-Version: 2.1
Name: touchstone-testing
Version: 1.4.2
Summary: Touchstone is a testing framework for your services that focuses on end-to-end and exploratory testing.
Home-page: https://github.com/shane-jansen/touchstone
Author: Shane Jansen
Author-email: shanejjansen@gmail.com
License: UNKNOWN
Platform: UNKNOWN
Classifier: Programming Language :: Python :: 3
Requires-Python: >=3.6
Requires-Dist: pyfiglet (~=0.8)
Requires-Dist: click (~=7.0)
Requires-Dist: pika (~=1.1)
Requires-Dist: pyyaml (~=5.4)
Requires-Dist: pymongo (~=3.10)
Requires-Dist: pymysql (~=0.9.3)
Requires-Dist: minio (~=5.0.7)
Requires-Dist: redis (~=3.5.3)
Requires-Dist: psycopg2-binary (~=2.9.3)
